coon/__init__.py
coon/analysis/__init__.py
coon/analysis/analyzer.py
coon/analysis/metrics.py
coon/cli/__init__.py
coon/cli/main.py
coon/core/__init__.py
coon/core/compressor.py
coon/core/config.py
coon/core/result.py
coon/data/__init__.py
coon/data/loader.py
coon/languages/__init__.py
coon/languages/base.py
coon/languages/registry.py
coon/languages/dart/__init__.py
coon/languages/dart/handler.py
coon/parser/__init__.py
coon/parser/ast_nodes.py
coon/parser/lexer.py
coon/parser/parser.py
coon/parser/tokens.py
coon/strategies/__init__.py
coon/strategies/aggressive.py
coon/strategies/ast_based.py
coon/strategies/base.py
coon/strategies/basic.py
coon/strategies/component_ref.py
coon/strategies/selector.py
coon/utils/__init__.py
coon/utils/formatter.py
coon/utils/registry.py
coon/utils/validator.py
coon-0.1.1.dist-info/METADATA
coon-0.1.1.dist-info/WHEEL
coon-0.1.1.dist-info/entry_points.txt
coon-0.1.1.dist-info/RECORD
