Metadata-Version: 2.4
Name: coon
Version: 0.1.1
Summary: Code-Oriented Object Notation - Token-efficient compression for Dart/Flutter code
Project-URL: Homepage, https://github.com/coon/coon
Project-URL: Documentation, https://github.com/coon/coon#readme
Project-URL: Repository, https://github.com/coon/coon
Project-URL: Issues, https://github.com/coon/coon/issues
Author: COON Contributors
License: MIT
Keywords: code-compression,compression,dart,flutter,llm,token-efficient
Classifier: Development Status :: 4 - Beta
Classifier: Intended Audience :: Developers
Classifier: License :: OSI Approved :: MIT License
Classifier: Operating System :: OS Independent
Classifier: Programming Language :: Python :: 3
Classifier: Programming Language :: Python :: 3.9
Classifier: Programming Language :: Python :: 3.10
Classifier: Programming Language :: Python :: 3.11
Classifier: Programming Language :: Python :: 3.12
Classifier: Topic :: Software Development :: Compilers
Classifier: Topic :: Text Processing :: Filters
Classifier: Typing :: Typed
Requires-Python: >=3.9
Provides-Extra: all
Requires-Dist: click>=8.0; extra == 'all'
Requires-Dist: mypy>=1.0; extra == 'all'
Requires-Dist: pytest-cov>=4.0; extra == 'all'
Requires-Dist: pytest>=7.0; extra == 'all'
Requires-Dist: ruff>=0.1; extra == 'all'
Provides-Extra: cli
Requires-Dist: click>=8.0; extra == 'cli'
Provides-Extra: dev
Requires-Dist: click>=8.0; extra == 'dev'
Requires-Dist: mypy>=1.0; extra == 'dev'
Requires-Dist: pytest-cov>=4.0; extra == 'dev'
Requires-Dist: pytest>=7.0; extra == 'dev'
Requires-Dist: ruff>=0.1; extra == 'dev'
